<?xml version="1.0" encoding="UTF-8"?>
<snippet><entry><trigger id="XML">attr</trigger><description>Attribute Definition</description><template>${attribute}=&quot;${value}&quot;${cursor}</template></entry><entry><trigger id="XML">altag</trigger><description>Long Generic Tag</description><template>&lt;${XML_TAG} ${attribute}=&quot;${value}&quot;&gt;
	${text}
&lt;/${XML_TAG}&gt;${cursor}</template></entry><entry><trigger id="XML">cmt</trigger><description>Add a comment</description><template>&lt;!-- ${comment} --&gt;${cursor}</template></entry><entry><trigger id="XML">tag</trigger><description>Generic Tag</description><template>&lt;${XML_TAG}&gt;${text}&lt;/${XML_TAG}&gt;${cursor}</template></entry><entry><trigger id="XML">xml</trigger><description>XML Header</description><template>&lt;?xml version=&quot;${1.0}&quot; encoding=&quot;${UTF-8}&quot;?&gt;${cursor}</template></entry><entry><trigger id="XML">ltag</trigger><description>Generic Tag Long Format</description><template>&lt;${XML_TAG}&gt;
	${text}
&lt;/${XML_TAG}&gt;${cursor}</template></entry><entry><trigger id="XML">atag</trigger><description>Short Tag With Attributes</description><template>&lt;${tag_name} ${name}=${value}&gt;${text}&lt;/${tag_name}&gt;${cursor}</template></entry><entry><trigger id="XML">stag</trigger><description>Short Generic Tag</description><template>&lt;${tag} /&gt;${cursor}</template></entry></snippet>